agentic_flows/__init__.py
agentic_flows/py.typed
agentic_flows/cli/__init__.py
agentic_flows/cli/main.py
agentic_flows/core/__init__.py
agentic_flows/core/authority.py
agentic_flows/core/errors.py
agentic_flows/core/ids.py
agentic_flows/core/verification_rules.py
agentic_flows/http_api/__init__.py
agentic_flows/http_api/app.py
agentic_flows/http_api/v1/__init__.py
agentic_flows/http_api/v1/schema.hash
agentic_flows/http_api/v1/schemas.py
agentic_flows/internal/__init__.py
agentic_flows/runtime/__init__.py
agentic_flows/runtime/artifact_store.py
agentic_flows/runtime/budget.py
agentic_flows/runtime/context.py
agentic_flows/runtime/verification_engine.py
agentic_flows/runtime/execution/__init__.py
agentic_flows/runtime/execution/agent_executor.py
agentic_flows/runtime/execution/dry_run_executor.py
agentic_flows/runtime/execution/live_executor.py
agentic_flows/runtime/execution/observer_executor.py
agentic_flows/runtime/execution/reasoning_executor.py
agentic_flows/runtime/execution/retrieval_executor.py
agentic_flows/runtime/execution/state_tracker.py
agentic_flows/runtime/execution/step_executor.py
agentic_flows/runtime/execution/phases/__init__.py
agentic_flows/runtime/execution/phases/execution.py
agentic_flows/runtime/execution/phases/finalization.py
agentic_flows/runtime/execution/phases/planning.py
agentic_flows/runtime/observability/_ANALYSIS.md
agentic_flows/runtime/observability/_CAPTURE.md
agentic_flows/runtime/observability/_REPORTING.md
agentic_flows/runtime/observability/_STORAGE.md
agentic_flows/runtime/observability/__init__.py
agentic_flows/runtime/observability/schema.hash
agentic_flows/runtime/observability/schema.sql
agentic_flows/runtime/observability/analysis/__init__.py
agentic_flows/runtime/observability/analysis/comparative_analysis.py
agentic_flows/runtime/observability/analysis/drift.py
agentic_flows/runtime/observability/analysis/flow_correlation.py
agentic_flows/runtime/observability/analysis/flow_invariants.py
agentic_flows-0.1.1.dist-info/METADATA
agentic_flows-0.1.1.dist-info/WHEEL
agentic_flows-0.1.1.dist-info/entry_points.txt
agentic_flows-0.1.1.dist-info/licenses/LICENSE
agentic_flows-0.1.1.dist-info/RECORD
