Metadata-Version: 2.4
Name: agentic-flows
Version: 0.1.1
Summary: Governed execution and replay with auditable non-determinism
Project-URL: Documentation, https://bijux.github.io/agentic-flows/
Project-URL: Repository, https://github.com/bijux/agentic-flows
Project-URL: Issues, https://github.com/bijux/agentic-flows/issues
Project-URL: Changelog, https://github.com/bijux/agentic-flows/blob/main/CHANGELOG.md
Author-email: Bijan Mousavi <mousavi.bijan@gmail.com>
License: Apache-2.0
License-File: LICENSE
Keywords: agents,audit,execution,governance,non-determinism,replay,reproducibility
Classifier: Development Status :: 3 - Alpha
Classifier: Environment :: Console
Classifier: Intended Audience :: Developers
Classifier: Intended Audience :: Science/Research
Classifier: License :: OSI Approved :: Apache Software License
Classifier: Operating System :: MacOS
Classifier: Operating System :: OS Independent
Classifier: Operating System :: POSIX
Classifier: Programming Language :: Python :: 3
Classifier: Programming Language :: Python :: 3 :: Only
Classifier: Programming Language :: Python :: 3.11
Classifier: Programming Language :: Python :: 3.12
Classifier: Programming Language :: Python :: 3.13
Classifier: Programming Language :: Python :: 3.14
Classifier: Programming Language :: Python :: Implementation :: CPython
Classifier: Topic :: Software Development :: Libraries
Classifier: Topic :: Utilities
Requires-Python: >=3.11
Requires-Dist: bijux-agent<0.2.0,>=0.1.0
Requires-Dist: bijux-cli<0.2.0,>=0.1.0
Requires-Dist: bijux-rag<0.2.0,>=0.1.0
Requires-Dist: bijux-rar<0.2.0,>=0.1.0
Requires-Dist: bijux-vex<0.2.0,>=0.1.0
Requires-Dist: duckdb<2.0.0,>=1.1.3
Requires-Dist: pydantic<3.0.0,>=2.0.2
Provides-Extra: api
Requires-Dist: fastapi<1.0,>=0.128; extra == 'api'
Requires-Dist: uvicorn<1.0,>=0.32; extra == 'api'
Provides-Extra: dev
Requires-Dist: bandit<2.0,>=1.7.10; extra == 'dev'
Requires-Dist: build<2.0,>=1.0.3; extra == 'dev'
Requires-Dist: codespell<3.0,>=2.3.0; extra == 'dev'
Requires-Dist: deptry<1.0,>=0.10.0; extra == 'dev'
Requires-Dist: fastapi<1.0,>=0.128; extra == 'dev'
Requires-Dist: httpx<1.0,>=0.27.0; extra == 'dev'
Requires-Dist: hypothesis-jsonschema<1.0,>=0.23.0; extra == 'dev'
Requires-Dist: hypothesis<7.0,>=6.103.0; extra == 'dev'
Requires-Dist: interrogate<2.0,>=1.7.0; extra == 'dev'
Requires-Dist: mkdocs-material<10.0,>=9.5.39; extra == 'dev'
Requires-Dist: mkdocs<2.0,>=1.6.1; extra == 'dev'
Requires-Dist: mypy<2.0,>=1.11.2; extra == 'dev'
Requires-Dist: pexpect<5.0,>=4.8.0; extra == 'dev'
Requires-Dist: pip-audit<3.0,>=2.7.3; extra == 'dev'
Requires-Dist: pydocstyle<7.0,>=6.2.1; extra == 'dev'
Requires-Dist: pyfakefs>=5.9.0; extra == 'dev'
Requires-Dist: pyright<2.0,>=1.1.320; extra == 'dev'
Requires-Dist: pytest-asyncio<2.0,>=1.0.0; extra == 'dev'
Requires-Dist: pytest-benchmark<5.0,>=4.0.0; extra == 'dev'
Requires-Dist: pytest-cov<7.0,>=6.2.1; extra == 'dev'
Requires-Dist: pytest-mock<4.0,>=3.14.1; extra == 'dev'
Requires-Dist: pytest-rerunfailures<14.0,>=13.0; extra == 'dev'
Requires-Dist: pytest-timeout<3.0,>=2.4.0; extra == 'dev'
Requires-Dist: pytest<9.0,>=8.4.1; extra == 'dev'
Requires-Dist: pytype>=2024.10.11; extra == 'dev'
Requires-Dist: pyyaml<7.0,>=6.0; extra == 'dev'
Requires-Dist: radon>=6.0.0; extra == 'dev'
Requires-Dist: reuse<6.0.0,>=4.0.0; extra == 'dev'
Requires-Dist: ruff<1.0,>=0.6.8; extra == 'dev'
Requires-Dist: types-colorama<1.0,>=0.0.14; extra == 'dev'
Requires-Dist: types-orjson<4.0,>=3.6.0; extra == 'dev'
Requires-Dist: types-pexpect<5.0,>=4.9.0; extra == 'dev'
Requires-Dist: types-psutil<7.0,>=6.0.0; extra == 'dev'
Requires-Dist: types-pyyaml<7.0,>=6.0.12; extra == 'dev'
Requires-Dist: typing-extensions<5.0,>=4.5.0; extra == 'dev'
Requires-Dist: vulture<3.0,>=2.7; extra == 'dev'
